README.md
setup.py
katex/__init__.py
katex/cli.py
katex/core.py
katex/models.py
katex/utils.py
katex.egg-info/PKG-INFO
katex.egg-info/SOURCES.txt
katex.egg-info/dependency_links.txt
katex.egg-info/entry_points.txt
katex.egg-info/requires.txt
katex.egg-info/top_level.txt